[
  {
    "question": "[File: aptos-core/third_party/move/move-vm/types/src/values/value_tests.rs] [Function: test_mem_swap()] [Address canonicalization] Do all address operations use canonical form? Can attackers use non-canonical addresses to bypass access control lists? (High)",
    "url": "https://deepwiki.com/search/-you-are-an-elite-aptos-blockc_292f2a04-4fef-41c2-a6ca-f9c741c1e3a3?mode=deep",
    "timestamp": "2026-01-20 10:03:26.805762",
    "report_generated": false
  },
  {
    "question": "[File: aptos-core/third_party/move/move-vm/types/src/values/value_tests.rs] [Function: test_mem_swap()] [Vector of addresses] VectorRef operations on address vectors (lines 171-172) - can address list manipulation bypass multi-sig requirements? (High)",
    "url": "https://deepwiki.com/search/-you-are-an-elite-aptos-blockc_61cf4dd8-9b97-4432-8a6c-98dab81e21a0?mode=deep",
    "timestamp": "2026-01-20 10:03:39.514121",
    "report_generated": false
  }
]