[
  {
    "question": "[File: aptos-core/ecosystem/indexer-grpc/transaction-filter/src/filters/user_transaction.rs] [Protobuf: Field presence] [Optional fields] Does protobuf optional field handling correctly distinguish between None (field not set) and Some(default_value), potentially causing filter logic errors? (Medium)",
    "url": "https://deepwiki.com/search/-you-are-an-elite-aptos-blockc_09733fa8-bb2b-47e2-97eb-853376e897aa?mode=deep",
    "timestamp": "2026-01-25 11:25:20.280954",
    "report_generated": false
  },
  {
    "question": "[File: aptos-core/ecosystem/indexer-grpc/transaction-filter/src/filters/user_\n\n### Citations\n\n**File:** ecosystem/indexer-grpc/transaction-filter/src/filters/user_transaction.rs (L1-295)\n```rust\n// Copyright (c) Aptos Foundation\n// SPDX-License-Identifier: Apache-2.0\n\nuse crate::{errors::FilterError, traits::Filterable, utils::standardize_address};\nuse anyhow::{anyhow, Error};\nuse aptos_protos::transaction::v1::{\n    multisig_transaction_payload, transaction::TxnData, transaction_payload, EntryFunctionId,\n    EntryFunctionPayload, Transaction, TransactionPayload,\n};\nuse once_cell::sync::OnceCell;\nuse serde::{Deserialize, Serialize};\n\n/// We use this for UserTransactions.\n/// We support UserPayload and MultisigPayload\n///\n/// Example:\n/// ```\n/// use aptos_transaction_filter::UserTransactionFilterBuilder;\n///\n/// let address =",
    "url": "https://deepwiki.com/search/-you-are-an-elite-aptos-blockc_9b9f9a7b-67a5-4e81-9257-a2ee02497cbc?mode=deep",
    "timestamp": "2026-01-25 11:25:32.541514",
    "report_generated": false
  }
]