[
  {
    "question": "[File: aptos-core/crates/indexer/src/models/stake_models/delegator_activities.rs] [Function: from_transaction()] [API type versioning] If aptos_api_types::Transaction adds new transaction types or changes existing structures, could this break compatibility with the parsing logic at lines 33-39? (Medium)",
    "url": "https://deepwiki.com/search/-you-are-an-elite-aptos-blockc_db32166c-c8d0-4765-b263-9f244715ddad?mode=deep",
    "timestamp": "2026-01-25 16:40:10.770462",
    "report_generated": false
  },
  {
    "question": "[File: aptos-core/crates/indexer/src/models/stake_models/delegator_activities.rs] [Struct definition] [Schema migration] If the delegated_staking_activities schema is migrated (e.g., adding new columns), could old code continue inserting with outdated struct definitions causing constraint violations? (Low)",
    "url": "https://deepwiki.com/search/-you-are-an-elite-aptos-blockc_35660d98-4485-4a60-9a1e-ac64cdeb9316?mode=deep",
    "timestamp": "2026-01-25 16:40:23.953747",
    "report_generated": false
  }
]