[
  {
    "question": "[File: aptos-core/crates/aptos-rest-client/src/client_builder.rs] [Function: ClientBuilder::build()] [Panic propagation] If the unwrap() in build() panics, does this properly clean up sensitive data (headers, API keys) from memory before aborting? (Medium)",
    "url": "https://deepwiki.com/search/-you-are-an-elite-aptos-blockc_ae2a9224-d120-44ee-a6a8-d60391876918?mode=deep",
    "timestamp": "2026-01-26 09:33:29.420785",
    "report_generated": false
  },
  {
    "question": "[File: aptos-core/crates/aptos-rest-client/src/client_builder.rs] [Function: ClientBuilder::timeout()] [Duration arithmetic overflow] Can Duration operations within reqwest cause arithmetic overflow when handling timeout calculations, leading to incorrect timeout behavior? (Low)",
    "url": "https://deepwiki.com/search/-you-are-an-elite-aptos-blockc_480650c7-ecc5-48fb-93b5-ad3b9d074a93?mode=deep",
    "timestamp": "2026-01-26 09:33:42.127190",
    "report_generated": false
  }
]